{
    "service_name": "telegram",
    "service_log": "stdout",

    "oracle_addr": "0.0.0.0",
    "oracle_port": 2355,
    "oracle_log": "stdout",
    "oracle_auth_cookie": "telegram_auth",
    "oracle_auth_secret": "YOUR_JWT_SECRET_HERE",
    "oracle_auth_users":
    [],
    
    "bot_api_key": "YOUR_TELEGRAM_BOT_API_KEY_HERE",
    "bot_chats":
    [
        {
            "id": "CHAT1_ID",
            "name": "CHAT1_NAME"
        },
        {
            "id": "CHAT2_ID",
            "name": "CHAT2_NAME"
        }
    ],
    "bot_users":
    [
        {
            "id": "USER1_ID",
            "name": "USER1_NAME"
        },
        {
            "id": "USER2_ID",
            "name": "USER2_NAME"
        }
    ],

    "lumen_address": "0.0.0.0",
    "lumen_port": 2350,
    "lumen_auth_username": "ABC",
    "lumen_auth_password": "XYZ",

    "warden_address": "0.0.0.0",
    "warden_port": 2351,
    "warden_auth_username": "ABC",
    "warden_auth_password": "XYZ",

    "scribble_address": "0.0.0.0",
    "scribble_port": 2354,
    "scribble_auth_username": "ABC",
    "scribble_auth_password": "XYZ",
    
    "notif_address": "0.0.0.0",
    "notif_port": 2356,
    "notif_auth_username": "ABC",
    "notif_auth_password": "XYZ"
}
